sym_types-1.2.0-py3.8-nspkg.pth
sym/enums/__init__.py
sym/enums/service_pb2.py
sym/messages/__init__.py
sym/messages/approval_pb2.py
sym/messages/dispatch_pb2.py
sym/messages/expiration_pb2.py
sym/messages/options_pb2.py
sym/messages/request_pb2.py
sym/messages/response_pb2.py
sym/models/__init__.py
sym/models/resource_pb2.py
sym/models/schema_pb2.py
sym/models/user_pb2.py
sym/models/uuid_pb2.py
sym_types-1.2.0.dist-info/LICENSE
sym_types-1.2.0.dist-info/METADATA
sym_types-1.2.0.dist-info/WHEEL
sym_types-1.2.0.dist-info/namespace_packages.txt
sym_types-1.2.0.dist-info/top_level.txt
sym_types-1.2.0.dist-info/RECORD
