Metadata-Version: 2.1
Name: sym-types
Version: 1.2.0
Summary: Generated protobufs for Sym types
Home-page: https://github.com/symopsio/types
Author: Sym Inc
Author-email: info@symops.io
License: UNKNOWN
Platform: UNKNOWN
Classifier: Programming Language :: Python :: 3
Classifier: License :: OSI Approved :: Apache Software License
Requires-Python: >=3.6
